pulldown_cmark-0.1.1.dist-info/METADATA
pulldown_cmark-0.1.1.dist-info/WHEEL
pulldown_cmark-0.1.1.dist-info/licenses/LICENSE
pulldown_cmark/__init__.py
pulldown_cmark/__init__.pyi
pulldown_cmark/pulldown_cmark.cpython-313-darwin.so
pulldown_cmark-0.1.1.dist-info/RECORD
