Metadata-Version: 2.4
Name: pulldown-cmark
Version: 0.1.1
License-File: LICENSE
Summary: A Python interface to pulldown-cmark.
Keywords: markdown
Home-Page: https://git.sr.ht/~orchid/pulldown-cmark-py
Author: Mohamad Makki <moe.m.makki@gmail.com>
Author-email: Mohamad Makki <moe.m.makki@gmail.com>
License: 0BSD
Requires-Python: >=3.13
Project-URL: Source Code, https://git.sr.ht/~orchid/pulldown-cmark-py
